dst_handler_ogre/__init__.py
dst_handler_ogre/constants.py
dst_handler_ogre/eet_to_utc.py
dst_handler_ogre-0.3.dist-info/METADATA
dst_handler_ogre-0.3.dist-info/WHEEL
dst_handler_ogre-0.3.dist-info/top_level.txt
dst_handler_ogre-0.3.dist-info/RECORD
